src/CharityEvent.py
src/DriverClass.py
src/Event.py
src/Events.py
src/NetworkingEvent.py
src/PartyEvent.py
src/Ticket.py
src/WorkshopEvent.py
src/__init__.py
tests/__init__.py
tests/test_generator.py
437_project-1.3.dist-info/METADATA
437_project-1.3.dist-info/WHEEL
437_project-1.3.dist-info/top_level.txt
437_project-1.3.dist-info/RECORD
